TestingPack/TestModule.py
TestingPack/__init__.py
my_extension/TestModule_cython.cp311-win_amd64.pyd
my_extension/__init__.py
TestingPack-1.0.1.dist-info/METADATA
TestingPack-1.0.1.dist-info/WHEEL
TestingPack-1.0.1.dist-info/top_level.txt
TestingPack-1.0.1.dist-info/RECORD
